{"is_source_file": false, "format": "", "description": "", "external_files": [], "external_methods": [], "published": [], "classes": [], "methods": [], "calls": [], "search-terms": [], "state": 2, "file_id": 9, "knowledge_revision": 25, "git_revision": "252c3524ae55b0cb96e26269e6f58bbdc2f34f5e", "hash": "aec40fdcbdacf2e95abf0e4c2969429d", "format-version": 4, "code-base-name": "portfolio_frontend", "filename": "portfolio_frontend/tsconfig.json", "revision_history": [{"25": "252c3524ae55b0cb96e26269e6f58bbdc2f34f5e"}]}